[
  {
    "model": "line.line",
    "pk": 651,
    "fields": {
      "line": "Мы шли дорогой горемык искать свою судьбу",
      "song": 21
    }
  },
  {
    "model": "line.line",
    "pk": 652,
    "fields": {
      "line": "В одной деревне на ночлег старик пустил в избу",
      "song": 21
    }
  },
  {
    "model": "line.line",
    "pk": 653,
    "fields": {
      "line": "Мы пили крепкий самогон - хозяин был к нам добр",
      "song": 21
    }
  },
  {
    "model": "line.line",
    "pk": 654,
    "fields": {
      "line": "Река бежала за окном, шумел сосновый бор",
      "song": 21
    }
  },
  {
    "model": "line.line",
    "pk": 655,
    "fields": {
      "line": "Я пью чуть больше чем могу, но меньше, чем хочу",
      "song": 21
    }
  },
  {
    "model": "line.line",
    "pk": 656,
    "fields": {
      "line": "Когда я пью, я не пою - я не пою, кричу",
      "song": 21
    }
  },
  {
    "model": "line.line",
    "pk": 657,
    "fields": {
      "line": "Hикто мне глотку не заткнет, не запретит мой пляс",
      "song": 21
    }
  },
  {
    "model": "line.line",
    "pk": 658,
    "fields": {
      "line": "Hо тут старик сказал: Дай я\" и начал свой рассказ",
      "song": 21
    }
  },
  {
    "model": "line.line",
    "pk": 659,
    "fields": {
      "line": "Иван был сказочно богат но не имел детей",
      "song": 21
    }
  },
  {
    "model": "line.line",
    "pk": 660,
    "fields": {
      "line": "Иван накрыл дубовый стол и пригласил гостей",
      "song": 21
    }
  },
  {
    "model": "line.line",
    "pk": 661,
    "fields": {
      "line": "Он переспал с одной вдовой - вдова сказала: \"Жди",
      "song": 21
    }
  },
  {
    "model": "line.line",
    "pk": 662,
    "fields": {
      "line": "Теперь зима, я разрешусь когда пойдут дожди\"",
      "song": 21
    }
  },
  {
    "model": "line.line",
    "pk": 663,
    "fields": {
      "line": "Иван счастливый захрапел, как красноармейский полк",
      "song": 21
    }
  },
  {
    "model": "line.line",
    "pk": 664,
    "fields": {
      "line": "Он крепко спал, когда во сне ему явился волк",
      "song": 21
    }
  },
  {
    "model": "line.line",
    "pk": 665,
    "fields": {
      "line": "Волк молвил: \"Если хочешь дочь - брось голову в огонь,",
      "song": 21
    }
  },
  {
    "model": "line.line",
    "pk": 666,
    "fields": {
      "line": "Захочешь сына - так отдай мне правую ладонь",
      "song": 21
    }
  },
  {
    "model": "line.line",
    "pk": 667,
    "fields": {
      "line": "Hе будь упрямым как осел, будь чистым как слеза,",
      "song": 21
    }
  },
  {
    "model": "line.line",
    "pk": 668,
    "fields": {
      "line": "Hо знай - захочешь обмануть - вдова родит козла\"",
      "song": 21
    }
  },
  {
    "model": "line.line",
    "pk": 669,
    "fields": {
      "line": "Сказав все это, волк исчез, Иван открыл глаза -",
      "song": 21
    }
  },
  {
    "model": "line.line",
    "pk": 670,
    "fields": {
      "line": "Вдова лежала на боку, поглаживая зад,",
      "song": 21
    }
  },
  {
    "model": "line.line",
    "pk": 671,
    "fields": {
      "line": "Иван напялил на себя ботинки и трусы,",
      "song": 21
    }
  },
  {
    "model": "line.line",
    "pk": 672,
    "fields": {
      "line": "Запряг трех быстрых вороных и кони понесли",
      "song": 21
    }
  },
  {
    "model": "line.line",
    "pk": 673,
    "fields": {
      "line": "Иван скакал четыре дня к кудыкиной горе",
      "song": 21
    }
  },
  {
    "model": "line.line",
    "pk": 674,
    "fields": {
      "line": "Там на горе жил друг Макар - весь в злате, серебре",
      "song": 21
    }
  },
  {
    "model": "line.line",
    "pk": 675,
    "fields": {
      "line": "Макар служил городовым и пропивал навар",
      "song": 21
    }
  },
  {
    "model": "line.line",
    "pk": 676,
    "fields": {
      "line": "Узнав о Ваниной беде, сказал: \"Споймаем тварь\"",
      "song": 21
    }
  },
  {
    "model": "line.line",
    "pk": 677,
    "fields": {
      "line": "Они расставили капканы вдоль лесных дорог",
      "song": 21
    }
  },
  {
    "model": "line.line",
    "pk": 678,
    "fields": {
      "line": "Попались лев, сова и заяц, но не попался волк",
      "song": 21
    }
  },
  {
    "model": "line.line",
    "pk": 679,
    "fields": {
      "line": "Друзья надыбали жратвы и ринулись в леса",
      "song": 21
    }
  },
  {
    "model": "line.line",
    "pk": 680,
    "fields": {
      "line": "Пока гонялись за волками - кончилась весна",
      "song": 21
    }
  },
  {
    "model": "line.line",
    "pk": 681,
    "fields": {
      "line": "Иван все лето пил вино, гуляя вдоль болот",
      "song": 21
    }
  },
  {
    "model": "line.line",
    "pk": 682,
    "fields": {
      "line": "Вдова сидела у окна и гладила живот",
      "song": 21
    }
  },
  {
    "model": "line.line",
    "pk": 683,
    "fields": {
      "line": "Однажды августовским днем, заслыша Ванин крик",
      "song": 21
    }
  },
  {
    "model": "line.line",
    "pk": 684,
    "fields": {
      "line": "Вдова схватила керосин и подожгла тростник",
      "song": 21
    }
  },
  {
    "model": "line.line",
    "pk": 685,
    "fields": {
      "line": "То был как есть условный знак - заполыхал пожар",
      "song": 21
    }
  },
  {
    "model": "line.line",
    "pk": 686,
    "fields": {
      "line": "Еще не наступил сентябрь, как прискакал Макар",
      "song": 21
    }
  },
  {
    "model": "line.line",
    "pk": 687,
    "fields": {
      "line": "Макар раздвинул камыши и глянул сквозь огонь",
      "song": 21
    }
  },
  {
    "model": "line.line",
    "pk": 688,
    "fields": {
      "line": "А там Иван без головы и где его ладонь",
      "song": 21
    }
  },
  {
    "model": "line.line",
    "pk": 689,
    "fields": {
      "line": "Макар ругнулся : \"е-мое\", но тихо, не со зла",
      "song": 21
    }
  },
  {
    "model": "line.line",
    "pk": 690,
    "fields": {
      "line": "Вдова не дождалась дождей и родила козла",
      "song": 21
    }
  },
  {
    "model": "line.line",
    "pk": 691,
    "fields": {
      "line": "С тех пор прошло двенадцать лет, Макар за взятки сел",
      "song": 21
    }
  },
  {
    "model": "line.line",
    "pk": 692,
    "fields": {
      "line": "Козла пустили в огород, и козлик окосел",
      "song": 21
    }
  },
  {
    "model": "line.line",
    "pk": 693,
    "fields": {
      "line": "Иван схоронен у болот - там тихо, ни души",
      "song": 21
    }
  },
  {
    "model": "line.line",
    "pk": 694,
    "fields": {
      "line": "И из груди его растут цветные камыши",
      "song": 21
    }
  },
  {
    "model": "line.line",
    "pk": 695,
    "fields": {
      "line": "Старик закончил, тихо встал, открыл нам сеновал",
      "song": 21
    }
  },
  {
    "model": "line.line",
    "pk": 696,
    "fields": {
      "line": "Друзья заснули сей же час и только я не спал",
      "song": 21
    }
  },
  {
    "model": "line.line",
    "pk": 697,
    "fields": {
      "line": "Я думал, глядя на луну, что стало со вдовой",
      "song": 21
    }
  },
  {
    "model": "line.line",
    "pk": 698,
    "fields": {
      "line": "Всю ночь сквозь храп моих друзей я слышал волчий вой",
      "song": 21
    }
  }
]